{
  "description": "Box Array Mesh is a component that is generated by brush tools and can be a cloud of boxes with points, sizes, and rotations.\n\nNote: ``Points``, ``Sizes``, ``Rotations``, ``Colors``, and ``UV_Scales`` arrays must be the same length for this component to work.",
  "category": "Assets:Procedural Meshes",
  "fields": {
    "Points": "List of positions that there should be boxes",
    "Sizes": "List of sizes for each box.",
    "Rotations": "List of rotations for each box.",
    "Colors": "List of colors for each box.",
    "ColorsProfile": "__TPL__. However, this is for every box in the array.",
    "UV_Scales": "List of UV scales for each box, scaling the material surface detail bigger or smaller."
  },
  "methods": {},
  "usage": "Use a brush tool from ``ResoniteEssentials/Tools/Brushes/Box Brushes`` and draw to make one of these with values already initialized.",
  "notes": [],
  "_source_url": "https://wiki.resonite.com/index.php?title=Component:BoxArrayMesh&action=raw"
}