{
  "description": "The ConvertibleDoubleDriver component is used to convert a value into a Double using the value's convert to Double method.",
  "category": "Uncategorized",
  "fields": {
    "Source": "The value to convert.",
    "Target": "The field to drive with ``Source`` converted into a Double."
  },
  "methods": {},
  "usage": "Used to convert values from one type into another via Components rather than ProtoFlux.",
  "notes": [],
  "_source_url": "https://wiki.resonite.com/index.php?title=Component:ConvertibleDoubleDriver&action=raw"
}