{
  "description": "When paired with a Begin Undo Batch, the End Undo Batch node will batch all previous undo steps after the previous Begin Undo Batch into one, ignoring all undo descriptions on all undo nodes between the two. This will make all the undo steps one undo press on the Context Menu of the user that impulsed the node chain.",
  "category": "",
  "fields": {
    "Input": "End the undo batch.",
    "Output": "Code to run after the undo batch."
  },
  "methods": {},
  "usage": "",
  "notes": [],
  "_source_url": "https://wiki.resonite.com/index.php?title=ProtoFlux:EndUndoBatch&action=raw"
}